<annotation>
  <folder>Dog</folder>
  <filename>dog (55)</filename>
  <path>D:\Practice\Tensorflow\Image\dogs\Dog\dog (55).jpg</path>
  <source>
    <database>Unknown</database>
  </source>
  <size>
    <width>297</width>
    <height>170</height>
    <depth>3</depth>
  </size>
  <segmented>0</segmented>
  <object>
    <name>dog</name>
    <pose>Unspecified</pose>
    <truncated>0</truncated>
    <difficult>0</difficult>
    <bndbox>
      <xmin>147</xmin>
      <ymin>54</ymin>
      <xmax>198</xmax>
      <ymax>107</ymax>
    </bndbox>
  </object>
</annotation>
